qilisdk/__init__.py
qilisdk/__init__.pyi
qilisdk/_logging.py
qilisdk/_optionals.py
qilisdk/logging_config.yaml
qilisdk/py.typed
qilisdk/settings.py
qilisdk/yaml.py
qilisdk/analog/__init__.py
qilisdk/analog/exceptions.py
qilisdk/analog/hamiltonian.py
qilisdk/analog/schedule.py
qilisdk/backends/__init__.py
qilisdk/backends/__init__.pyi
qilisdk/backends/backend.py
qilisdk/backends/cuda_backend.py
qilisdk/backends/qutip_backend.py
qilisdk/core/__init__.py
qilisdk/core/exceptions.py
qilisdk/core/interpolator.py
qilisdk/core/model.py
qilisdk/core/parameterizable.py
qilisdk/core/qtensor.py
qilisdk/core/result.py
qilisdk/core/variables.py
qilisdk/cost_functions/__init__.py
qilisdk/cost_functions/cost_function.py
qilisdk/cost_functions/model_cost_function.py
qilisdk/cost_functions/observable_cost_function.py
qilisdk/digital/__init__.py
qilisdk/digital/ansatz.py
qilisdk/digital/circuit.py
qilisdk/digital/circuit_transpiler.py
qilisdk/digital/exceptions.py
qilisdk/digital/gates.py
qilisdk/digital/circuit_transpiler_passes/__init__.py
qilisdk/digital/circuit_transpiler_passes/circuit_transpiler_pass.py
qilisdk/digital/circuit_transpiler_passes/decompose_multi_controlled_gates_pass.py
qilisdk/digital/circuit_transpiler_passes/numeric_helpers.py
qilisdk/experiments/__init__.py
qilisdk/experiments/experiment_functional.py
qilisdk/experiments/experiment_result.py
qilisdk/functionals/__init__.py
qilisdk/functionals/functional.py
qilisdk/functionals/functional_result.py
qilisdk/functionals/sampling.py
qilisdk/functionals/sampling_result.py
qilisdk/functionals/time_evolution.py
qilisdk/functionals/time_evolution_result.py
qilisdk/functionals/variational_program.py
qilisdk/functionals/variational_program_result.py
qilisdk/optimizers/__init__.py
qilisdk/optimizers/optimizer.py
qilisdk/optimizers/optimizer_result.py
qilisdk/optimizers/scipy_optimizer.py
qilisdk/speqtrum/__init__.py
qilisdk/speqtrum/__init__.pyi
qilisdk/speqtrum/keyring.py
qilisdk/speqtrum/speqtrum.py
qilisdk-0.1.7.dist-info/METADATA
qilisdk-0.1.7.dist-info/WHEEL
qilisdk-0.1.7.dist-info/licenses/LICENCE
qilisdk-0.1.7.dist-info/RECORD
