Metadata-Version: 2.4
Name: qilisdk
Version: 0.1.7
Summary: QiliSDK is a Python framework for writing digital and analog quantum algorithms and executing them across multiple quantum backends. Its modular design streamlines the development process and enables easy integration with a variety of quantum platforms.
Project-URL: Homepage, https://github.com/qilimanjaro-tech/qilisdk
Project-URL: Documentation, https://qilimanjaro-tech.github.io/qilisdk/
Project-URL: Source, https://github.com/qilimanjaro-tech/qilisdk
Project-URL: Issues, https://github.com/qilimanjaro-tech/qilisdk/issues
Project-URL: Changelog, https://github.com/qilimanjaro-tech/qilisdk/blob/main/CHANGELOG.md
Author-email: Qilimanjaro Quantum Tech <info@qilimanjaro.tech>
License-File: LICENCE
Keywords: analog quantum computing,digital quantum computing,qilimanjaro,quantum computing
Classifier: Development Status :: 4 - Beta
Classifier: Environment :: Console
Classifier: Intended Audience :: Developers
Classifier: Intended Audience :: Science/Research
Classifier: License :: OSI Approved :: Apache Software License
Classifier: Operating System :: POSIX :: Linux
Classifier: Programming Language :: Python :: 3
Classifier: Programming Language :: Python :: 3.11
Classifier: Programming Language :: Python :: 3.12
Classifier: Programming Language :: Python :: 3.13
Classifier: Topic :: Scientific/Engineering
Classifier: Topic :: Scientific/Engineering :: Physics
Classifier: Topic :: Scientific/Engineering :: Quantum Computing
Requires-Python: >=3.11
Requires-Dist: dill>=0.3.9
Requires-Dist: loguru>=0.7.3
Requires-Dist: matplotlib>=3.10.7
Requires-Dist: mkl-service>=2.4.2; sys_platform != 'darwin'
Requires-Dist: numpy>=2.2.0
Requires-Dist: pydantic-settings>=2.11.0
Requires-Dist: pydantic>=2.12.3
Requires-Dist: ruamel-yaml>=0.18.16
Requires-Dist: scipy<1.16.3,>=1.15; sys_platform != 'darwin'
Requires-Dist: scipy>=1.16.3; sys_platform == 'darwin'
Provides-Extra: cuda
Requires-Dist: cuda-quantum-cu12==0.13.0; extra == 'cuda'
Provides-Extra: openfermion
Requires-Dist: openfermion>=1.7.1; extra == 'openfermion'
Provides-Extra: qutip
Requires-Dist: qutip-qip>=0.4.1; extra == 'qutip'
Requires-Dist: qutip>=5.2.2; extra == 'qutip'
Provides-Extra: speqtrum
Requires-Dist: httpx==0.28.1; extra == 'speqtrum'
Requires-Dist: keyring>=25.6.0; extra == 'speqtrum'
Requires-Dist: keyrings-alt>=5.0.2; extra == 'speqtrum'
